gcphelpers/__init__.py
gcphelpers/prometheus/__init__.py
gcphelpers/secretmanager/__init__.py
gcphelpers/slack/__init__.py
gcphelpers/storage/__init__.py
gcphelpers-0.0.11.dist-info/WHEEL
gcphelpers-0.0.11.dist-info/METADATA
gcphelpers-0.0.11.dist-info/RECORD
