Metadata-Version: 2.1
Name: gcphelpers
Version: 0.0.11
Summary: Helpers for GCP functions
Author: Alex Orfanos
Author-email: alexandros@mailerlite.com
Requires-Python: >=3.8,<4.0
Classifier: Programming Language :: Python :: 3
Classifier: Programming Language :: Python :: 3.10
Classifier: Programming Language :: Python :: 3.8
Classifier: Programming Language :: Python :: 3.9
Requires-Dist: google-cloud-secret-manager (>=2.7.2,<3.0.0)
Requires-Dist: google-cloud-storage (>=1.42.3,<2.0.0)
Requires-Dist: pre-commit (>=2.15.0,<3.0.0)
Requires-Dist: prometheus-client (>=0.11.0,<0.12.0)
Requires-Dist: slack-sdk (>=3.11.2,<4.0.0)
